mlpush/__init__.py
mlpush-0.0.1.dist-info/METADATA
mlpush-0.0.1.dist-info/WHEEL
mlpush-0.0.1.dist-info/top_level.txt
mlpush-0.0.1.dist-info/RECORD
